hmr/__init__.py
hmr/api.py
hmr/reload.py
python_hmr-0.2.0.dist-info/LICENSE
python_hmr-0.2.0.dist-info/WHEEL
python_hmr-0.2.0.dist-info/METADATA
python_hmr-0.2.0.dist-info/RECORD
