Metadata-Version: 2.1
Name: python-hmr
Version: 0.2.0
Summary: Hot module reload for python
Author-email: Mr-Milk <yb97643@um.edu.mo>
Requires-Python: >=3.8
Classifier: License :: OSI Approved :: MIT License
Requires-Dist: watchdog
Project-URL: Home, https://github.com/mr-milk/python-hmr
